MANIFEST.in
MIT-LICENSE
README.md
setup.cfg
setup.py
./nfelib/__init__.py
nfelib/__init__.py
nfelib/bindings/__init__.py
nfelib/bindings/bpe/__init__.py
nfelib/bindings/bpe/v1_0/__init__.py
nfelib/bindings/bpe/v1_0/bpe_tipos_basico_v1_00.py
nfelib/bindings/bpe/v1_0/bpe_tm_v1_00.py
nfelib/bindings/bpe/v1_0/bpe_v1_00.py
nfelib/bindings/bpe/v1_0/cons_sit_bpe_tipos_basico_v1_00.py
nfelib/bindings/bpe/v1_0/cons_sit_bpe_v1_00.py
nfelib/bindings/bpe/v1_0/cons_stat_serv_bpe_tipos_basico_v1_00.py
nfelib/bindings/bpe/v1_0/cons_stat_serv_bpe_v1_00.py
nfelib/bindings/bpe/v1_0/ev_alteracao_poltrona_v1_00.py
nfelib/bindings/bpe/v1_0/ev_canc_bpe_v1_00.py
nfelib/bindings/bpe/v1_0/ev_excesso_bagagem_v1_00.py
nfelib/bindings/bpe/v1_0/ev_nao_emb_bpe_v1_00.py
nfelib/bindings/bpe/v1_0/evento_bpe_tipos_basico_v1_00.py
nfelib/bindings/bpe/v1_0/evento_bpe_v1_00.py
nfelib/bindings/bpe/v1_0/proc_bpe_tm_v1_00.py
nfelib/bindings/bpe/v1_0/proc_bpe_v1_00.py
nfelib/bindings/bpe/v1_0/proc_evento_bpe_v1_00.py
nfelib/bindings/bpe/v1_0/ret_bpe_v1_00.py
nfelib/bindings/bpe/v1_0/ret_cons_sit_bpe_v1_00.py
nfelib/bindings/bpe/v1_0/ret_cons_stat_serv_bpe_v1_00.py
nfelib/bindings/bpe/v1_0/ret_evento_bpe_v1_00.py
nfelib/bindings/bpe/v1_0/tipos_geral_bpe_v1_00.py
nfelib/bindings/bpe/v1_0/xmldsig_core_schema_v1_01.py
nfelib/bindings/cte/__init__.py
nfelib/bindings/cte/v3_0/__init__.py
nfelib/bindings/cte/v3_0/cons_reci_cte_tipos_basico_v3_00.py
nfelib/bindings/cte/v3_0/cons_reci_cte_v3_00.py
nfelib/bindings/cte/v3_0/cons_sit_cte_tipos_basico_v3_00.py
nfelib/bindings/cte/v3_0/cons_sit_cte_v3_00.py
nfelib/bindings/cte/v3_0/cons_stat_serv_cte_v3_00.py
nfelib/bindings/cte/v3_0/cons_stat_serv_tipos_basico_v3_00.py
nfelib/bindings/cte/v3_0/cte_modal_aereo_v3_00.py
nfelib/bindings/cte/v3_0/cte_modal_aquaviario_v3_00.py
nfelib/bindings/cte/v3_0/cte_modal_dutoviario_v3_00.py
nfelib/bindings/cte/v3_0/cte_modal_ferroviario_v3_00.py
nfelib/bindings/cte/v3_0/cte_modal_rodoviario_os_v3_00.py
nfelib_xsdata.egg-info/PKG-INFO
nfelib_xsdata.egg-info/SOURCES.txt
nfelib_xsdata.egg-info/dependency_links.txt
nfelib_xsdata.egg-info/requires.txt
nfelib_xsdata.egg-info/top_level.txt