Metadata-Version: 2.1
Name: nfelib-xsdata
Version: 0.9.2
Summary: nfelib: electronic invoicing library for Brazil
Home-page: https://github.com/akretion/nfelib
Author: Raphaël Valyi
Author-email: "raphael.valyi@akretion.com.br"
License: MIT
Project-URL: Source, https://github.com/akretion/nfelib
Keywords: e-invoicing,NFe,ERP,Odoo
Platform: UNKNOWN
Classifier: Intended Audience :: Developers
Classifier: License :: OSI Approved :: MIT License
Classifier: Operating System :: OS Independent
Classifier: Programming Language :: Python
Classifier: Programming Language :: Python :: 3
Classifier: Programming Language :: Python :: 3 :: Only
Classifier: Programming Language :: Python :: 3.6
Classifier: Programming Language :: Python :: 3.7
Classifier: Programming Language :: Python :: 3.8
Classifier: Programming Language :: Python :: 3.9
Classifier: Programming Language :: Python :: Implementation :: CPython
Classifier: Programming Language :: Python :: Implementation :: PyPy
Classifier: Topic :: Software Development :: Code Generators
Classifier: Topic :: Text Processing :: Markup :: XML
Requires-Python: >=3.6
Provides-Extra: test
License-File: MIT-LICENSE
